Triumvirate-0.5.0.dist-info/RECORD
Triumvirate-0.5.0.dist-info/WHEEL
Triumvirate-0.5.0.dist-info/top_level.txt
Triumvirate-0.5.0.dist-info/LICENCE
Triumvirate-0.5.0.dist-info/METADATA
triumvirate/_particles.cpython-310-aarch64-linux-gnu.so
triumvirate/_field.cpython-310-aarch64-linux-gnu.so
triumvirate/winconv.py
triumvirate/threept.py
triumvirate/_particles.pxd
triumvirate/_field.pxd
triumvirate/transforms.py
triumvirate/_valid_install.py
triumvirate/twopt.py
triumvirate/parameters.pyx
triumvirate/_threept.cpython-310-aarch64-linux-gnu.so
triumvirate/catalogue.py
triumvirate/_fftlog.pyx
triumvirate/parameters.pxd
triumvirate/__init__.py
triumvirate/dataobjs.pxd
triumvirate/parameters.cpython-310-aarch64-linux-gnu.so
triumvirate/dataobjs.pyx
triumvirate/_threept.pyx
triumvirate/_particles.pyx
triumvirate/logger.py
triumvirate/_mpitools.py
triumvirate/_fftlog.pxd
triumvirate/_twopt.cpython-310-aarch64-linux-gnu.so
triumvirate/fieldmesh.py
triumvirate/dataobjs.cpython-310-aarch64-linux-gnu.so
triumvirate/_arrayops.py
triumvirate/_field.pyx
triumvirate/_fftlog.cpython-310-aarch64-linux-gnu.so
triumvirate/_twopt.pyx
triumvirate/resources/params_template.ini
triumvirate/resources/params_template.yml
triumvirate/include/maths.hpp
triumvirate/include/io.hpp
triumvirate/include/arrayops.hpp
triumvirate/include/fftlog.hpp
triumvirate/include/threept.hpp
triumvirate/include/particles.hpp
triumvirate/include/field.hpp
triumvirate/include/twopt.hpp
triumvirate/include/dataobjs.hpp
triumvirate/include/parameters.hpp
triumvirate/include/monitor.hpp
triumvirate/src/parameters.cpp
triumvirate/src/twopt.cpp
triumvirate/src/monitor.cpp
triumvirate/src/fftlog.cpp
triumvirate/src/io.cpp
triumvirate/src/maths.cpp
triumvirate/src/field.cpp
triumvirate/src/dataobjs.cpp
triumvirate/src/arrayops.cpp
triumvirate/src/particles.cpp
triumvirate/src/threept.cpp
Triumvirate.libs/libfftw3-b7546720.so.3.5.5
Triumvirate.libs/libgslcblas-cf1da87e.so.0.0.0
Triumvirate.libs/libfftw3_omp-813bb571.so.3.5.5
Triumvirate.libs/libgsl-f7298b36.so.23.1.0
Triumvirate.libs/libgomp-98df74fd.so.1.0.0
