Metadata-Version: 2.1
Name: Triumvirate
Version: 0.5.0
Summary: Three-point clustering measurements in large-scale structure analyses.
Home-page: https://mikeswang.github.io/Triumvirate
Author: Mike S Wang, Naonori S Sugiyama
Maintainer: Mike S Wang
Maintainer-email: Mike S Wang <32841762+MikeSWang@users.noreply.github.com>
License: GNU GENERAL PUBLIC LICENSE
Project-URL: Documentation, https://triumvirate.readthedocs.io/
Project-URL: Source, https://github.com/MikeSWang/Triumvirate
Project-URL: Changelog, https://github.com/MikeSWang/Triumvirate/blob/main/CHANGELOG.md
Platform: Linux
Platform: Darwin
Classifier: License :: OSI Approved :: GNU General Public License v3 (GPLv3)
Classifier: License :: OSI Approved :: GNU General Public License v3 or later (GPLv3+)
Classifier: Operating System :: MacOS
Classifier: Operating System :: POSIX :: Linux
Classifier: Programming Language :: C++
Classifier: Programming Language :: Cython
Classifier: Programming Language :: Python
Classifier: Programming Language :: Python :: 3
Classifier: Programming Language :: Python :: 3 :: Only
Classifier: Topic :: Scientific/Engineering :: Astronomy
Classifier: Topic :: Scientific/Engineering :: Information Analysis
Classifier: Topic :: Scientific/Engineering :: Physics
Requires-Python: >=3.10
License-File: LICENCE
Requires-Dist: numpy >=1.23
Requires-Dist: scipy >=1.13
Requires-Dist: sympy >=1.12.1
Requires-Dist: astropy >=4.2
Requires-Dist: pyyaml >=5.1
Requires-Dist: tqdm
Provides-Extra: mpi
Requires-Dist: mpi4py >=3.1.5 ; extra == 'mpi'
Provides-Extra: nbk
Requires-Dist: nbodykit ; extra == 'nbk'
